__init__.py
notebook_doc/__init__.py
notebook_doc/doc_functions.py
notebook_doc/test.py
notebook_doc-0.2.1.dist-info/LICENSE
notebook_doc-0.2.1.dist-info/METADATA
notebook_doc-0.2.1.dist-info/WHEEL
notebook_doc-0.2.1.dist-info/top_level.txt
notebook_doc-0.2.1.dist-info/RECORD
