Metadata-Version: 2.1
Name: notebook-doc
Version: 0.2.1
Summary: A package to create documentation for functions in Databricks notebooks
Author-email: Hiran Hasanka <hiranhasanka@gmail.com>
Project-URL: Homepage, https://github.com/theSLWayne/notebook-doc
Project-URL: Bug Tracker, https://github.com/theSLWayne/notebook-doc/issues
Classifier: Programming Language :: Python :: 3
Classifier: License :: OSI Approved :: MIT License
Classifier: Operating System :: OS Independent
Requires-Python: >=3.7
License-File: LICENSE
Requires-Dist: Jinja2 (>=3.1.0)
Requires-Dist: docstring-parser (>=0.15)
